Metadata-Version: 2.1
Name: tencent-mta-client
Version: 0.1.3
Summary: tencent mta client is python sdk encapsulate for tencent mta api
Home-page: https://github.com/jamesqin-cn/tencent-mta-client
Author: jamesqin
Author-email: jamesqin@vip.qq.com
License: MIT
Platform: any
Classifier: Intended Audience :: Developers
Classifier: Operating System :: OS Independent
Classifier: Topic :: Utilities
Classifier: Topic :: Software Development :: Libraries :: Python Modules
Classifier: Programming Language :: Python
Classifier: Programming Language :: Python :: 2
Classifier: Programming Language :: Python :: 2.7
Classifier: Programming Language :: Python :: 3
Classifier: Programming Language :: Python :: 3.7
